{"tags":[{"name":"电影","link":"movie"},{"name":"旅行","link":"travel"},{"name":"读书","link":"book"},{"name":"邮票","link":"stamp"}],"lists":[{"title":"《云中行走》","tag":"movie","date":"2016.01.23","href":"20160123-6"},{"title":"《星球大战：原力觉醒》","tag":"movie","date":"2016.01.17","href":"20160117-11"},{"title":"东天目山","tag":"travel","date":"2016.01.01","href":"20160101-4"},{"title":"《火星救援》","tag":"movie","date":"2015.11.28","href":"20151128-6"},{"title":"《1980 年代的爱情》","tag":"movie","date":"2015.11.07","href":"20151107-12"},{"title":"《绝命海拔》","tag":"movie","date":"2015.11.06","href":"20151106-6"},{"title":"《蚁人》","tag":"movie","date":"2015.10.23","href":"20151023-4"},{"title":"《头脑特工队》","tag":"movie","date":"2015.10.09","href":"20151009-7"},{"title":"《我就是想停下来，看看这个世界》","tag":"book","date":"2015.09.08","href":"20150908-16"},{"title":"《讲故事的人 - 斯皮尔伯格传》","tag":"book","date":"2015.08.29","href":"20150829-16"},{"title":"内蒙草原、沙漠行","tag":"travel","date":"2015.08.29","href":"20150829-8"},{"title":"《滚蛋吧，肿瘤君》","tag":"movie","date":"2015.08.29","href":"20150829-9"},{"title":"《白银时代 - 2015》","tag":"book","date":"2015.08.18","href":"20150818-13"},{"title":"《白银时代 - 未来世界》","tag":"book","date":"2015.08.17","href":"20150817-13"},{"title":"《白银时代 - 白银时代》","tag":"book","date":"2015.08.16","href":"20150816-13"},{"title":"《游戏改变世界》","tag":"book","date":"2015.07.23","href":"20150723-8"},{"title":"《捉妖记》","tag":"movie","date":"2015.07.21","href":"20150721-5"},{"title":"《黄金时代 - 我的阴阳两界》","tag":"book","date":"2015.07.17","href":"20150717-15"},{"title":"《黄金时代 - 革命时期的爱情》","tag":"book","date":"2015.07.12","href":"20150712-16"},{"title":"大树王国 - 西天目","tag":"travel","date":"2015.07.05","href":"20150705-10"},{"title":"《木星上行》","tag":"movie","date":"2015.06.28","href":"20150628-6"},{"title":"《黄金时代 - 似水流年》","tag":"book","date":"2015.06.28","href":"20150628-13"},{"title":"《超能查派》","tag":"movie","date":"2015.06.22","href":"20150622-6"},{"title":"龙门古镇","tag":"travel","date":"2015.06.21","href":"20150621-4"},{"title":"《黄金时代 - 三十而立》","tag":"book","date":"2015.06.14","href":"20150614-13"},{"title":"《失孤》","tag":"movie","date":"2015.06.12","href":"20150612-4"},{"title":"《黄金时代 - 黄金时代》","tag":"book","date":"2015.06.12","href":"20150612-13"},{"title":"泰国甲米、普吉跟团游","tag":"travel","date":"2015.06.06","href":"20150606-10"},{"title":"《何以笙箫默》","tag":"movie","date":"2015.06.05","href":"20150605-7"},{"title":"《活着》","tag":"book","date":"2015.06.04","href":"20150604-4"},{"title":"《美丽心灵》","tag":"movie","date":"2015.05.27","href":"20150527-6"},{"title":"《万物生长》","tag":"movie","date":"2015.05.24","href":"20150524-6"},{"title":"《疯传》","tag":"book","date":"2015.05.24","href":"20150524-4"},{"title":"《暴疯语》","tag":"movie","date":"2015.05.23","href":"20150523-5"},{"title":"《复仇者联盟 2 - 奥创纪元》","tag":"movie","date":"2015.05.17","href":"20150517-16"},{"title":"《左耳》","tag":"movie","date":"2015.05.10","href":"20150510-4"},{"title":"《狼图腾》","tag":"movie","date":"2015.05.10","href":"20150510-5"},{"title":"《战狼》","tag":"movie","date":"2015.05.06","href":"20150506-4"},{"title":"《致命追踪》","tag":"movie","date":"2015.05.06","href":"20150506-6"},{"title":"《王牌特工》","tag":"movie","date":"2015.05.05","href":"20150505-6"},{"title":"《速度与激情 7》","tag":"movie","date":"2015.05.05","href":"20150505-9"},{"title":"新西兰奇幻之旅","tag":"travel","date":"2015.05.01","href":"20150501-7"},{"title":"《龙门飞甲》","tag":"movie","date":"2012.01.09","href":"20120109-6"},{"title":"《深度谜案》","tag":"movie","date":"2012.01.08","href":"20120108-6"},{"title":"《那些年，我们一起追的女孩》","tag":"movie","date":"2012.01.08","href":"20120108-14"},{"title":"《金陵十三钗》","tag":"movie","date":"2012.01.08","href":"20120108-7"},{"title":"《铁甲钢拳》","tag":"movie","date":"2011.11.19","href":"20111119-6"},{"title":"《失恋 33 天》","tag":"movie","date":"2011.11.14","href":"20111114-9"},{"title":"《星空》","tag":"movie","date":"2011.11.08","href":"20111108-4"},{"title":"《转山》","tag":"movie","date":"2011.11.07","href":"20111107-4"},{"title":"《猩球崛起》","tag":"movie","date":"2011.10.29","href":"20111029-6"},{"title":"《一夜迷情》","tag":"movie","date":"2011.10.20","href":"20111020-6"},{"title":"《夺命深渊》","tag":"movie","date":"2011.09.20","href":"20110920-6"},{"title":"《窃听风云 2》","tag":"movie","date":"2011.08.30","href":"20110830-8"},{"title":"《赛车总动员 2》","tag":"movie","date":"2011.08.30","href":"20110830-9"},{"title":"《哈利·波特与死亡圣器（下）》","tag":"movie","date":"2011.08.14","href":"20110814-15"},{"title":"《蓝精灵》","tag":"movie","date":"2011.08.14","href":"20110814-5"},{"title":"《钢的琴》","tag":"movie","date":"2011.07.25","href":"20110725-5"},{"title":"《假装情侣》","tag":"movie","date":"2011.06.28","href":"20110628-6"},{"title":"《速度与激情 5》","tag":"movie","date":"2011.06.03","href":"20110603-9"},{"title":"《功夫熊猫 2》","tag":"movie","date":"2011.05.29","href":"20110529-8"},{"title":"《加勒比海盗 4：惊涛怪浪》","tag":"movie","date":"2011.05.29","href":"20110529-14"},{"title":"《宇宙英雄之超银河传说》","tag":"movie","date":"2011.05.21","href":"20110521-12"},{"title":"《最爱》","tag":"movie","date":"2011.05.17","href":"20110517-4"},{"title":"《危情三日》","tag":"movie","date":"2011.05.04","href":"20110504-6"},{"title":"《倩女幽魂》","tag":"movie","date":"2011.04.25","href":"20110425-6"},{"title":"常熟行","tag":"travel","date":"2011.04.18","href":"20110418-3"},{"title":"《战国》","tag":"movie","date":"2011.04.17","href":"20110417-4"},{"title":"《美少女特工队》","tag":"movie","date":"2011.04.17","href":"20110417-8"},{"title":"云南行","tag":"travel","date":"2011.04.17","href":"20110417-3"},{"title":"《守望者：罪恶迷途》","tag":"movie","date":"2011.03.27","href":"20110327-10"},{"title":"《刀剑笑》","tag":"movie","date":"2011.03.27","href":"20110327-5"},{"title":"《观音山》","tag":"movie","date":"2011.03.07","href":"20110307-5"},{"title":"《最强喜事》","tag":"movie","date":"2011.02.15","href":"20110215-6"},{"title":"《武林外传》","tag":"movie","date":"2011.01.28","href":"20110128-6"},{"title":"《新少林寺》","tag":"movie","date":"2011.01.23","href":"20110123-6"},{"title":"《纳尼亚传奇 3：黎明踏浪号》","tag":"movie","date":"2011.01.10","href":"20110110-15"},{"title":"《非诚勿扰 2》","tag":"movie","date":"2010.12.26","href":"20101226-8"},{"title":"《让子弹飞》","tag":"movie","date":"2010.12.17","href":"20101217-6"},{"title":"《大笑江湖》","tag":"movie","date":"2010.12.05","href":"20101205-6"},{"title":"《赵氏孤儿》","tag":"movie","date":"2010.12.04","href":"20101204-6"},{"title":"《哈利·波特与死亡圣器（上）》","tag":"movie","date":"2010.11.26","href":"20101126-15"},{"title":"《爱出色》","tag":"movie","date":"2010.11.11","href":"20101111-5"},{"title":"《密室之不可告人》","tag":"movie","date":"2010.11.07","href":"20101107-9"},{"title":"《大秦帝国 - 帝国烽烟》","tag":"book","date":"2010.11.02","href":"20101102-13"},{"title":"《西风烈》","tag":"movie","date":"2010.11.02","href":"20101102-5"},{"title":"《爱情维修站》","tag":"movie","date":"2010.10.24","href":"20101024-7"},{"title":"《大秦帝国 - 铁血文明（下卷）》","tag":"book","date":"2010.10.23","href":"20101023-17"},{"title":"《绝命岛》","tag":"movie","date":"2010.10.17","href":"20101017-5"},{"title":"南浔无锡行","tag":"travel","date":"2010.10.11","href":"20101011-5"},{"title":"《庐山恋 2010》","tag":"movie","date":"2010.10.08","href":"20101008-10"},{"title":"《狄仁杰之通天帝国》","tag":"movie","date":"2010.10.07","href":"20101007-10"},{"title":"《米香》","tag":"movie","date":"2010.10.02","href":"20101002-4"},{"title":"《剑雨》","tag":"movie","date":"2010.09.29","href":"20100929-4"},{"title":"大明山","tag":"travel","date":"2010.09.23","href":"20100923-3"},{"title":"《精武风云·陈真》","tag":"movie","date":"2010.09.22","href":"20100922-9"},{"title":"《山楂树之恋》","tag":"movie","date":"2010.09.16","href":"20100916-7"},{"title":"《初恋红豆冰》","tag":"movie","date":"2010.09.12","href":"20100912-7"},{"title":"《盗梦空间》","tag":"movie","date":"2010.09.05","href":"20100905-6"},{"title":"《娜娜的玫瑰战争》","tag":"movie","date":"2010.09.01","href":"20100901-9"},{"title":"《大劫难》","tag":"movie","date":"2010.08.28","href":"20100828-5"},{"title":"《线人》","tag":"movie","date":"2010.08.25","href":"20100825-4"},{"title":"《龙凤店》","tag":"movie","date":"2010.08.24","href":"20100824-5"},{"title":"《喋血孤城》","tag":"movie","date":"2010.08.19","href":"20100819-6"},{"title":"《翡翠明珠》","tag":"movie","date":"2010.08.18","href":"20100818-6"},{"title":"《恋爱通告》","tag":"movie","date":"2010.08.13","href":"20100813-6"},{"title":"《全城戒备》","tag":"movie","date":"2010.08.07","href":"20100807-6"},{"title":"《唐山大地震》","tag":"movie","date":"2010.07.24","href":"20100724-7"},{"title":"《唐伯虎点秋香 2 之四大才子》","tag":"movie","date":"2010.07.13","href":"20100713-16"},{"title":"《枪王之王》","tag":"movie","date":"2010.07.10","href":"20100710-6"},{"title":"《大秦帝国 - 铁血文明（上卷）》","tag":"book","date":"2010.07.06","href":"20100706-17"},{"title":"《嘻游记》","tag":"movie","date":"2010.07.06","href":"20100706-5"},{"title":"《功夫梦》","tag":"movie","date":"2010.06.30","href":"20100630-5"},{"title":"《80'后》","tag":"movie","date":"2010.06.27","href":"20100627-6"},{"title":"《海洋天堂》","tag":"movie","date":"2010.06.22","href":"20100622-6"},{"title":"《玩具总动员 3》","tag":"movie","date":"2010.06.16","href":"20100616-9"},{"title":"安吉三日游","tag":"travel","date":"2010.06.16","href":"20100616-5"},{"title":"《驯龙高手》","tag":"movie","date":"2010.05.25","href":"20100525-6"},{"title":"《叶问 2》","tag":"movie","date":"2010.04.28","href":"20100428-6"},{"title":"《东风雨》","tag":"movie","date":"2010.04.27","href":"20100427-5"},{"title":"《岁月神偷》","tag":"movie","date":"2010.04.24","href":"20100424-6"},{"title":"《杜拉拉升职记》","tag":"movie","date":"2010.04.22","href":"20100422-8"},{"title":"《大秦帝国 - 阳谋春秋（下卷）》","tag":"book","date":"2010.04.11","href":"20100411-17"},{"title":"《越光宝盒》","tag":"movie","date":"2010.03.24","href":"20100324-6"},{"title":"《大兵小将》","tag":"movie","date":"2010.02.24","href":"20100224-6"},{"title":"2009 我最喜欢的 5 部电影","tag":"movie","date":"2010.02.21","href":"20100221-16"},{"title":"《大秦帝国 - 阳谋春秋（上卷）》","tag":"book","date":"2010.02.19","href":"20100219-17"},{"title":"《苏乞儿》","tag":"movie","date":"2010.02.09","href":"20100209-5"},{"title":"《锦衣卫》","tag":"movie","date":"2010.02.04","href":"20100204-5"},{"title":"《孔子》","tag":"movie","date":"2010.01.27","href":"20100127-4"},{"title":"《大秦帝国 - 金戈铁马（下卷）》","tag":"book","date":"2010.01.24","href":"20100124-17"},{"title":"《阿凡达》","tag":"movie","date":"2010.01.10","href":"20100110-5"},{"title":"《十月围城》","tag":"movie","date":"2009.12.30","href":"20091230-6"},{"title":"《大秦帝国 - 金戈铁马（上卷）》","tag":"book","date":"2009.12.24","href":"20091224-17"},{"title":"《三枪拍案惊奇》","tag":"movie","date":"2009.12.16","href":"20091216-8"},{"title":"《大秦帝国 - 国命纵横（下卷）》","tag":"book","date":"2009.11.29","href":"20091129-17"},{"title":"《大秦帝国 - 国命纵横（上卷）》","tag":"book","date":"2009.11.15","href":"20091115-17"},{"title":"《倚天屠龙记》","tag":"movie","date":"2009.11.14","href":"20091114-7"},{"title":"《大秦帝国 - 黑色裂变（下卷）》","tag":"book","date":"2009.10.30","href":"20091030-17"},{"title":"横店秦王宫游玩","tag":"travel","date":"2009.10.25","href":"20091025-7"},{"title":"《大秦帝国 - 黑色裂变（上卷）》","tag":"book","date":"2009.10.11","href":"20091011-17"},{"title":"《风声》","tag":"movie","date":"2009.09.30","href":"20090930-4"},{"title":"《麦田》","tag":"movie","date":"2009.09.29","href":"20090929-4"},{"title":"《建国大业》","tag":"movie","date":"2009.09.23","href":"20090923-6"},{"title":"《原来这才是春秋 - 争霸》","tag":"book","date":"2009.09.07","href":"20090907-14"},{"title":"《机器侠》","tag":"movie","date":"2009.09.02","href":"20090902-5"},{"title":"《非常完美》","tag":"movie","date":"2009.08.15","href":"20090815-6"},{"title":"《大内密探零零狗》","tag":"movie","date":"2009.08.10","href":"20090810-9"},{"title":"《特种部队 - 眼镜蛇的崛起》","tag":"movie","date":"2009.08.08","href":"20090808-15"},{"title":"《原来这才是春秋 - 称霸》","tag":"book","date":"2009.08.08","href":"20090808-14"},{"title":"《飞屋环游记》","tag":"movie","date":"2009.08.05","href":"20090805-7"},{"title":"《我的机器人女友》","tag":"movie","date":"2009.08.01","href":"20090801-9"},{"title":"《窃听风云》","tag":"movie","date":"2009.07.28","href":"20090728-6"},{"title":"《不要只做我告诉你的事，请做需要做的事》","tag":"book","date":"2009.07.14","href":"20090714-20"},{"title":"《冰河世纪 3》","tag":"movie","date":"2009.07.08","href":"20090708-8"},{"title":"《终结者 2018》","tag":"movie","date":"2009.06.10","href":"20090610-10"},{"title":"《郑和下西洋》","tag":"movie","date":"2009.05.17","href":"20090517-7"},{"title":"《拉贝日记》","tag":"movie","date":"2009.05.01","href":"20090501-6"},{"title":"去南京玩了一圈儿。。。","tag":"travel","date":"2009.04.26","href":"20090426-11"},{"title":"《南京！南京！》","tag":"movie","date":"2009.04.25","href":"20090425-8"},{"title":"《PTU2：机动部队》","tag":"movie","date":"2009.04.17","href":"20090417-11"},{"title":"流浪数学家","tag":"book","date":"2009.04.14","href":"20090414-5"},{"title":"《高考 1977》","tag":"movie","date":"2009.04.05","href":"20090405-9"},{"title":"《贫民窟的百万富翁》","tag":"movie","date":"2009.03.29","href":"20090329-10"},{"title":"《他的国》","tag":"book","date":"2009.02.21","href":"20090221-5"},{"title":"《游剑江湖》","tag":"movie","date":"2009.02.21","href":"20090221-6"},{"title":"圆明园赏荷","tag":"travel","date":"2008.08.24","href":"20080824-5"}]}